tangany_settlement_api_sdk/__init__.py
tangany_settlement_api_sdk/auth/__init__.py
tangany_settlement_api_sdk/auth/authenticator.py
tangany_settlement_api_sdk/auth/credentials.py
tangany_settlement_api_sdk/endpoints/__init__.py
tangany_settlement_api_sdk/endpoints/account_balances.py
tangany_settlement_api_sdk/endpoints/accounts.py
tangany_settlement_api_sdk/endpoints/asset_balances.py
tangany_settlement_api_sdk/endpoints/assets.py
tangany_settlement_api_sdk/endpoints/funding_deposit.py
tangany_settlement_api_sdk/endpoints/funding_withdrawals.py
tangany_settlement_api_sdk/endpoints/fundings.py
tangany_settlement_api_sdk/endpoints/ledgers.py
tangany_settlement_api_sdk/endpoints/report_results.py
tangany_settlement_api_sdk/endpoints/reports.py
tangany_settlement_api_sdk/endpoints/response_handler.py
tangany_settlement_api_sdk/endpoints/transactions.py
tangany_settlement_api_sdk/settlement_client.py
tangany_settlement_api_sdk-0.1.6.dist-info/LICENSE
tangany_settlement_api_sdk-0.1.6.dist-info/METADATA
tangany_settlement_api_sdk-0.1.6.dist-info/WHEEL
tangany_settlement_api_sdk-0.1.6.dist-info/RECORD
