Metadata-Version: 2.1
Name: tangany_settlement_api_sdk
Version: 0.1.6
Summary: Inofficial Python SDK for consuming Tangany Settlement API
License: MIT
Author: Marcel
Author-email: marcel.nellesen@tangany.com
Requires-Python: >=3.10,<4.0
Classifier: License :: OSI Approved :: MIT License
Classifier: Programming Language :: Python :: 3
Classifier: Programming Language :: Python :: 3.10
Classifier: Programming Language :: Python :: 3.11
Classifier: Programming Language :: Python :: 3.12
Requires-Dist: attr (>=0.3.2,<0.4.0)
Requires-Dist: requests (>=2.31.0,<3.0.0)
Requires-Dist: urllib3 (>=2.1.0,<3.0.0)
